air_kit/__init__.py
air_kit/application.py
air_kit/decorators.py
air_kit/environment.py
air_kit/errors.py
air_kit/logging.py
air_kit/process.py
air_kit/profiler.py
air_kit/telegram_bot.py
air_kit/telemetry.py
air_kit/worker.py
air_kit-0.1.9.dist-info/LICENSE.md
air_kit-0.1.9.dist-info/METADATA
air_kit-0.1.9.dist-info/WHEEL
air_kit-0.1.9.dist-info/top_level.txt
air_kit-0.1.9.dist-info/RECORD
